pyacaia/__init__.py
pyacaia-0.4.0.dist-info/LICENSE
pyacaia-0.4.0.dist-info/METADATA
pyacaia-0.4.0.dist-info/WHEEL
pyacaia-0.4.0.dist-info/top_level.txt
pyacaia-0.4.0.dist-info/RECORD
