Metadata-Version: 2.1
Name: pyacaia
Version: 0.4.0
Summary: A Python module to interact with ACAIA scales via bluetooth (BLE)
Home-page: https://github.com/lucapinello/pyacaia
Author: Luca Pinello
Author-email: UNKNOWN
License: GPLv3
Platform: UNKNOWN
Requires-Dist: bluepy
